kotonebot/__init__.py
kotonebot/errors.py
kotonebot/util.py
kotonebot/backend/__init__.py
kotonebot/backend/bot.py
kotonebot/backend/color.py
kotonebot/backend/core.py
kotonebot/backend/dispatch.py
kotonebot/backend/flow_controller.py
kotonebot/backend/image.py
kotonebot/backend/loop.py
kotonebot/backend/ocr.py
kotonebot/backend/preprocessor.py
kotonebot/backend/context/__init__.py
kotonebot/backend/context/context.py
kotonebot/backend/context/task_action.py
kotonebot/backend/debug/__init__.py
kotonebot/backend/debug/entry.py
kotonebot/backend/debug/mock.py
kotonebot/backend/debug/server.py
kotonebot/backend/debug/vars.py
kotonebot/client/__init__.py
kotonebot/client/device.py
kotonebot/client/fast_screenshot.py
kotonebot/client/protocol.py
kotonebot/client/registration.py
kotonebot/client/scaler.py
kotonebot/client/host/__init__.py
kotonebot/client/host/adb_common.py
kotonebot/client/host/custom.py
kotonebot/client/host/leidian_host.py
kotonebot/client/host/mumu12_host.py
kotonebot/client/host/protocol.py
kotonebot/client/host/windows_common.py
kotonebot/client/implements/__init__.py
kotonebot/client/implements/adb.py
kotonebot/client/implements/remote_windows.py
kotonebot/client/implements/uiautomator2.py
kotonebot/client/implements/windows.py
kotonebot/client/implements/nemu_ipc/__init__.py
kotonebot/client/implements/nemu_ipc/external_renderer_ipc.py
kotonebot/client/implements/nemu_ipc/nemu_ipc.py
kotonebot/config/__init__.py
kotonebot/config/base_config.py
kotonebot/config/config.py
kotonebot/config/manager.py
kotonebot/core/__init__.py
kotonebot/core/entities/base.py
kotonebot/core/entities/compound.py
kotonebot/core/entities/ocr.py
kotonebot/core/entities/template_match.py
kotonebot/devtools/__init__.py
kotonebot/devtools/mirror.py
kotonebot/devtools/cli/__init__.py
kotonebot/devtools/cli/main.py
kotonebot/devtools/project/__init__.py
kotonebot/devtools/project/project.py
kotonebot/devtools/project/scanner.py
kotonebot/devtools/project/schema.py
kotonebot-0.6.0.dist-info/licenses/LICENSE
kotonebot-0.6.0.dist-info/METADATA
kotonebot-0.6.0.dist-info/WHEEL
kotonebot-0.6.0.dist-info/entry_points.txt
kotonebot-0.6.0.dist-info/top_level.txt
kotonebot-0.6.0.dist-info/RECORD
