Metadata-Version: 2.4
Name: kotonebot
Version: 0.6.0
Summary: Kotonebot is game automation library based on computer vision technology, works for Windows and Android.
Requires-Python: >=3.10
License-File: LICENSE
Requires-Dist: opencv-python~=4.10
Requires-Dist: rapidocr_onnxruntime~=1.4
Requires-Dist: scikit-image~=0.25
Requires-Dist: thefuzz~=0.22
Requires-Dist: pydantic~=2.10
Requires-Dist: ksaa-res~=0.2
Requires-Dist: typing-extensions~=4.12
Requires-Dist: python-dotenv~=1.0
Requires-Dist: onnxruntime~=1.14
Requires-Dist: numpy
Requires-Dist: mouse>=0.7.1
Provides-Extra: android
Requires-Dist: adbutils>=2.8; extra == "android"
Requires-Dist: uiautomator2>=3.2; extra == "android"
Provides-Extra: windows
Requires-Dist: pywin32; extra == "windows"
Requires-Dist: ahk>=1.8; extra == "windows"
Requires-Dist: win11toast>=0.35; extra == "windows"
Requires-Dist: psutil>=6.1; extra == "windows"
Provides-Extra: dev
Requires-Dist: fastapi~=0.115; extra == "dev"
Requires-Dist: uvicorn~=0.34; extra == "dev"
Requires-Dist: python-multipart~=0.0; extra == "dev"
Requires-Dist: websockets~=14.1; extra == "dev"
Requires-Dist: psutil~=6.1; extra == "dev"
Requires-Dist: twine~=6.1; extra == "dev"
Requires-Dist: build; extra == "dev"
Requires-Dist: snakeviz; extra == "dev"
Requires-Dist: tomli; python_version < "3.11" and extra == "dev"
Requires-Dist: dataclass-wizard; extra == "dev"
Requires-Dist: jinja2~=3.1; extra == "dev"
Requires-Dist: tqdm~=4.67; extra == "dev"
Provides-Extra: all
Requires-Dist: kotonebot[android,dev,windows]; extra == "all"
Dynamic: license-file
